[
  {
    "text": "Tu palabra es una lámpara a mis pies y una luz en mi camino.",
    "ref": "Salmo 119:105"
  },
  {
    "text": "El Señor es mi pastor; nada me faltará.",
    "ref": "Salmo 23:1"
  },
  {
    "text": "Dios es nuestro amparo y fortaleza, nuestro pronto auxilio en las tribulaciones.",
    "ref": "Salmo 46:1"
  },
  {
    "text": "El corazón alegre hermosea el rostro.",
    "ref": "Proverbios 15:13"
  },
  {
    "text": "Cristo en vosotros, la esperanza de gloria.",
    "ref": "Colosenses 1:27"
  },
  {
    "text": "La oración es el abrir del corazón a Dios como a un amigo.",
    "ref": "El Camino a Cristo, p. 93"
  }
]
